mcp_ptm_ppt_generator/Science_template.pptx
mcp_ptm_ppt_generator/__init__.py
mcp_ptm_ppt_generator/generate_ppt.py
mcp_ptm_ppt_generator/template.pptx
mcp_ptm_ppt_generator-1.0.7.dist-info/METADATA
mcp_ptm_ppt_generator-1.0.7.dist-info/WHEEL
mcp_ptm_ppt_generator-1.0.7.dist-info/entry_points.txt
mcp_ptm_ppt_generator-1.0.7.dist-info/RECORD
