Metadata-Version: 2.4
Name: mcp-ptm-ppt-generator
Version: 1.0.7
Summary: An MCP tool for generating student-report PowerPoint presentations.
Author: Nishtha Sharma
Requires-Python: >=3.9
Requires-Dist: fastmcp
Requires-Dist: pydantic
Requires-Dist: python-pptx
